knarto.py
knarto-0.1.5.dist-info/METADATA
knarto-0.1.5.dist-info/WHEEL
knarto-0.1.5.dist-info/entry_points.txt
knarto-0.1.5.dist-info/top_level.txt
knarto-0.1.5.dist-info/RECORD
